api_extractor/__init__.py
api_extractor/py.typed
api_extractor-0.1.4.dist-info/LICENSE
api_extractor-0.1.4.dist-info/METADATA
api_extractor-0.1.4.dist-info/WHEEL
api_extractor-0.1.4.dist-info/top_level.txt
api_extractor-0.1.4.dist-info/RECORD
